{
  "generatedAt": "2026-06-17T03:30:17.633Z",
  "leaderboardDate": "2026-06-16",
  "source": {
    "baseUrl": "https://api.monkeytype.com/leaderboards/daily",
    "sourceUrlTemplate": "https://api.monkeytype.com/leaderboards/daily?pageSize={pageSize}&page={page}&mode={mode}&mode2={jsonStringMode2}&language={language}&daysBefore={daysBefore}",
    "daysBefore": 1,
    "pageSize": 200,
    "mode": "time",
    "mode2": "60",
    "language": "spanish",
    "pages": [
      0,
      1,
      2,
      3,
      4
    ]
  },
  "data": {
    "entries": [
      {
        "wpm": 157.6,
        "acc": 97.11,
        "timestamp": 1781643913000,
        "raw": 165.2,
        "consistency": 83.18,
        "uid": "7hhc7Lg6VUR6Ith6I8zEQIoTSAc2",
        "name": "derivamdc",
        "rank": 1
      },
      {
        "wpm": 140.2,
        "acc": 98.75,
        "timestamp": 1781599801000,
        "raw": 143,
        "consistency": 86.36,
        "uid": "pUza4KLY1SeinwrcvVkojria0492",
        "name": "sanrafael",
        "rank": 2
      },
      {
        "wpm": 136.62,
        "acc": 98.7,
        "timestamp": 1781585542000,
        "raw": 136.62,
        "consistency": 76.98,
        "uid": "2qAs77FojEP0008btYQ2CSX0iED3",
        "name": "llakolnlen",
        "rank": 3
      },
      {
        "wpm": 134.4,
        "acc": 95.58,
        "timestamp": 1781623440000,
        "raw": 146,
        "consistency": 82.62,
        "uid": "22KthNrIf3e8ccKWogxZfXc16Zm1",
        "name": "Liher",
        "discordId": "868609698553815121",
        "discordAvatar": "83eaf771bda2fb68ac69d721f99773bd",
        "rank": 4
      },
      {
        "wpm": 127.82,
        "acc": 100,
        "timestamp": 1781588759000,
        "raw": 127.82,
        "consistency": 86.2,
        "uid": "zRyKst4ZN4aw3GDzt7A2FxjfuSx1",
        "name": "idirak",
        "rank": 5
      },
      {
        "wpm": 123.82,
        "acc": 91.62,
        "timestamp": 1781628835000,
        "raw": 147.02,
        "consistency": 78.41,
        "uid": "Ah2veIGoFQabsGLkEJOT3hJzygv1",
        "name": "Socramyos",
        "discordId": "627557954907799552",
        "discordAvatar": "e95034d6910ebb596638b36ebb69c8d0",
        "rank": 6
      },
      {
        "wpm": 122.6,
        "acc": 94.01,
        "timestamp": 1781582375000,
        "raw": 135.4,
        "consistency": 78.62,
        "uid": "YdYETp6LIxV7O2RHLto1wRCrEPF2",
        "name": "daninsola",
        "rank": 7
      },
      {
        "wpm": 121.62,
        "acc": 98.55,
        "timestamp": 1781631539000,
        "raw": 121.62,
        "consistency": 76.49,
        "uid": "dNv1u1Jy9AVFrTQJaf0zhpNj2OG3",
        "name": "Alfafuentes",
        "rank": 8
      },
      {
        "wpm": 110.82,
        "acc": 96.95,
        "timestamp": 1781653776000,
        "raw": 118.22,
        "consistency": 84.51,
        "uid": "2iAOMue9aoRDrSKPf78bwdq4jhw2",
        "name": "frostbitntest",
        "rank": 9
      },
      {
        "wpm": 110.42,
        "acc": 94,
        "timestamp": 1781653241000,
        "raw": 123.42,
        "consistency": 80.38,
        "uid": "YzWLuIZSV9SFslDh8delRKfT7AK2",
        "name": "KuakTv",
        "discordId": "630982479989178378",
        "discordAvatar": "00b19f3e0c63af404aaa8eb3e66e7399",
        "rank": 10
      },
      {
        "wpm": 108.4,
        "acc": 93.27,
        "timestamp": 1781631885000,
        "raw": 115.2,
        "consistency": 67.04,
        "uid": "ItXbi2dnehhTqTPb3iUiDPMbHFm2",
        "name": "Red",
        "discordId": "321747018168926209",
        "discordAvatar": "d409421b5fe789bd930d57fd7c8edb83",
        "rank": 11
      },
      {
        "wpm": 108.22,
        "acc": 98.01,
        "timestamp": 1781630849000,
        "raw": 108.22,
        "consistency": 74.39,
        "uid": "F8F9ARuxYcVDOCseWiZwwwagKSw2",
        "name": "Dr.Leosan",
        "rank": 12
      },
      {
        "wpm": 107.6,
        "acc": 97.65,
        "timestamp": 1781622156000,
        "raw": 110.8,
        "consistency": 87.91,
        "uid": "wXRkBEEkPCf5AKKHgChLzpJWsR52",
        "name": "Tuccini98",
        "rank": 13
      },
      {
        "wpm": 107,
        "acc": 95.57,
        "timestamp": 1781579071000,
        "raw": 107.8,
        "consistency": 73.43,
        "uid": "cBtXlYZy1KT5A7y9OovKUS5Rjzl2",
        "name": "dyanwav",
        "rank": 14
      },
      {
        "wpm": 106.4,
        "acc": 97.97,
        "timestamp": 1781573676000,
        "raw": 106.4,
        "consistency": 78.99,
        "uid": "U1K0sS76rtguTuFk8a71jce80MM2",
        "name": "gatouski",
        "discordId": "1217313341501079564",
        "discordAvatar": "6306e97774556aad147683bba462f82c",
        "rank": 15
      },
      {
        "wpm": 105.6,
        "acc": 93.59,
        "timestamp": 1781634008000,
        "raw": 109.4,
        "consistency": 72.6,
        "uid": "Cui15kQPVHP8scNQTwRtEYdiV4g1",
        "name": "Thorn1105",
        "rank": 16
      },
      {
        "wpm": 98.6,
        "acc": 98.6,
        "timestamp": 1781619716000,
        "raw": 98.6,
        "consistency": 80.45,
        "uid": "VaJ6oa3oaHRrkVGsPRhvY2Vxp7C3",
        "name": "dperico",
        "rank": 17
      },
      {
        "wpm": 98.22,
        "acc": 94.4,
        "timestamp": 1781585238000,
        "raw": 105.62,
        "consistency": 73.52,
        "uid": "nM82KKhQjGfOvAqYf4juQbv9Y8I3",
        "name": "AngelTomas.dev",
        "rank": 18
      },
      {
        "wpm": 98.2,
        "acc": 95.06,
        "timestamp": 1781640614000,
        "raw": 98.2,
        "consistency": 65.2,
        "uid": "BcXAZ7nyujgRpqZSob1zPVwaJZg2",
        "name": "AlexSpanish",
        "discordId": "499707325880336385",
        "discordAvatar": "041d7f4b7ebebc9eed16452ba14d2045",
        "rank": 19
      },
      {
        "wpm": 94.95,
        "acc": 96.8,
        "timestamp": 1781583580000,
        "raw": 96.35,
        "consistency": 67.68,
        "uid": "HVKmJptBkRSpErtwhG6R02BA0dO2",
        "name": "AxelCalci",
        "rank": 20
      },
      {
        "wpm": 93.62,
        "acc": 93.93,
        "timestamp": 1781570728000,
        "raw": 93.62,
        "consistency": 65.08,
        "uid": "ZZU9uskOG2PvWHMK0icBDN8zNGR2",
        "name": "Marcelo_MC",
        "rank": 21
      },
      {
        "wpm": 92.78,
        "acc": 97.49,
        "timestamp": 1781652618000,
        "raw": 92.78,
        "consistency": 71.47,
        "uid": "5VyZzq5B1qfvsJwQa9TUcyro87U2",
        "name": "drdiazzz",
        "rank": 22
      },
      {
        "wpm": 89.23,
        "acc": 97.6,
        "timestamp": 1781641618000,
        "raw": 89.23,
        "consistency": 78.21,
        "uid": "p5fZhmh2liMYKVSi7X1NX35PbY13",
        "name": "Coleccionista227",
        "rank": 23
      },
      {
        "wpm": 89,
        "acc": 96.55,
        "timestamp": 1781628732000,
        "raw": 89,
        "consistency": 63.37,
        "uid": "sGD9oAUIqEQyjJbW9TmteFHfQqI2",
        "name": "fdez",
        "rank": 24
      },
      {
        "wpm": 88.61,
        "acc": 98.68,
        "timestamp": 1781603939000,
        "raw": 89.81,
        "consistency": 79.19,
        "uid": "Nth9VfmRnzehcOC8VDkfkS85tL72",
        "name": "oscarrico9",
        "discordId": "933262540174159902",
        "discordAvatar": "4cb5191beedf7cb90ff3b4f90d7bb01b",
        "rank": 25
      },
      {
        "wpm": 85.21,
        "acc": 95.4,
        "timestamp": 1781618371000,
        "raw": 85.21,
        "consistency": 69.58,
        "uid": "woe896yrcIQfT42ORkFCU6uChJh2",
        "name": "jarbz",
        "rank": 26
      },
      {
        "wpm": 85,
        "acc": 92.51,
        "timestamp": 1781629747000,
        "raw": 86,
        "consistency": 64.51,
        "uid": "fEoNnVMkMpcOcjUjpwrx4Toagqu1",
        "name": "MethaVic",
        "rank": 27
      },
      {
        "wpm": 84,
        "acc": 99.76,
        "timestamp": 1781621894000,
        "raw": 84,
        "consistency": 69.49,
        "uid": "9ud09tTpg8QfH0oJObY2vLA08n23",
        "name": "Pinchin",
        "rank": 28
      },
      {
        "wpm": 82.2,
        "acc": 95.6,
        "timestamp": 1781640458000,
        "raw": 82.2,
        "consistency": 71.22,
        "uid": "7xzLQzpA6TMi0FbLksqIaFvifMB3",
        "name": "IanY13",
        "rank": 29
      },
      {
        "wpm": 81.81,
        "acc": 93.72,
        "timestamp": 1781650011000,
        "raw": 88.21,
        "consistency": 76.49,
        "uid": "aKmgHpt03GauUIFMGdqflQ3ZJjJ3",
        "name": "TiagoA",
        "rank": 30
      },
      {
        "wpm": 80.01,
        "acc": 95.27,
        "timestamp": 1781627686000,
        "raw": 80.01,
        "consistency": 71.58,
        "uid": "6fTVxJ4WT2cEyY2u3g3Pt1qy3DJ3",
        "name": "Inciart3bi_",
        "rank": 31
      },
      {
        "wpm": 78.99,
        "acc": 92.26,
        "timestamp": 1781619593000,
        "raw": 95.38,
        "consistency": 76.08,
        "uid": "qn2rEjuPgmXa1m9ZIiHHD4pLtp93",
        "name": "mr007",
        "rank": 32
      },
      {
        "wpm": 77.61,
        "acc": 93.65,
        "timestamp": 1781595811000,
        "raw": 84.01,
        "consistency": 71.27,
        "uid": "NS0NtxmI9FXQtbWUnVllS3y35bm1",
        "name": "Aletheia07",
        "discordId": "646904470516531201",
        "discordAvatar": "ad10a071cb3b75d762953b690f2fbdf4",
        "rank": 33
      },
      {
        "wpm": 76.41,
        "acc": 97.75,
        "timestamp": 1781605690000,
        "raw": 78.61,
        "consistency": 79.75,
        "uid": "8uWuw9WjplbJixmSf42Ezz6WF642",
        "name": "DalaiSama",
        "rank": 34
      },
      {
        "wpm": 76.36,
        "acc": 97.04,
        "timestamp": 1781614645000,
        "raw": 80.56,
        "consistency": 78.02,
        "uid": "jxS6VePnYYNKTyBZUt96yAAvnlk1",
        "name": "dimitri_more",
        "rank": 35
      },
      {
        "wpm": 76,
        "acc": 97.95,
        "timestamp": 1781628221000,
        "raw": 77.4,
        "consistency": 75.66,
        "uid": "3SCJ1hE1AGbxYxB1LBxeeHPdj6l2",
        "name": "alvaroglake",
        "rank": 36
      },
      {
        "wpm": 75.8,
        "acc": 96.19,
        "timestamp": 1781595137000,
        "raw": 84,
        "consistency": 74.18,
        "uid": "c5im9E3Cz7Sgeo1xgFvZduh2tdF2",
        "name": "Fish_Alone",
        "discordId": "943559761184579595",
        "discordAvatar": "18196683465e0f22461f7658661eb430",
        "rank": 37
      },
      {
        "wpm": 75.6,
        "acc": 88.74,
        "timestamp": 1781580464000,
        "raw": 101.2,
        "consistency": 80.84,
        "uid": "QoZoIWSvcMV54Bc8BXQZpKjhlpe2",
        "name": "LeoJimenez",
        "rank": 38
      },
      {
        "wpm": 75.21,
        "acc": 93.17,
        "timestamp": 1781625048000,
        "raw": 75.21,
        "consistency": 64.75,
        "uid": "Efiz7jUiKtXVxUdGLnrrhW3ZQvE3",
        "name": "David72",
        "rank": 39
      },
      {
        "wpm": 74.2,
        "acc": 97.13,
        "timestamp": 1781618524000,
        "raw": 74.2,
        "consistency": 71.39,
        "uid": "MxY5eHCuXaUfNwm1VSNePu0TLv12",
        "name": "JavierVerCan",
        "rank": 40
      },
      {
        "wpm": 73.81,
        "acc": 94.7,
        "timestamp": 1781639407000,
        "raw": 73.81,
        "consistency": 60.01,
        "uid": "XfGjbGX4PqOxx2NyDAM4fYFqQLp1",
        "name": "Brayan_csk",
        "rank": 41
      },
      {
        "wpm": 73.4,
        "acc": 99.2,
        "timestamp": 1781635825000,
        "raw": 75,
        "consistency": 85.18,
        "uid": "nTpUBmoRzaWEO2JdeE0TSEoHW5V2",
        "name": "tata02",
        "rank": 42
      },
      {
        "wpm": 71.81,
        "acc": 96.29,
        "timestamp": 1781654346000,
        "raw": 71.81,
        "consistency": 67.38,
        "uid": "eGHLZIL6D5OjLyErbn9HvFrmmht1",
        "name": "faelrano",
        "rank": 43
      },
      {
        "wpm": 70.61,
        "acc": 93.93,
        "timestamp": 1781624908000,
        "raw": 70.61,
        "consistency": 65.27,
        "uid": "FyQZLZB7diS52WKKE4gnaH314LC3",
        "name": "Haremfcker",
        "discordId": "515373706718085121",
        "discordAvatar": "8932e89d0922039b1c236aad66652d93",
        "rank": 44
      },
      {
        "wpm": 70,
        "acc": 95.65,
        "timestamp": 1781569640000,
        "raw": 70,
        "consistency": 64.73,
        "uid": "f0fvg2bKpaftdeMiUqK7nSyluka2",
        "name": "gayim",
        "discordId": "202308184927371264",
        "discordAvatar": "bae4f270fe360cdd4151fe6429fc0b73",
        "rank": 45
      },
      {
        "wpm": 68.81,
        "acc": 94.34,
        "timestamp": 1781632048000,
        "raw": 74.61,
        "consistency": 71.49,
        "uid": "9lxjl5kR9HbKst4jSc8cujr40uO2",
        "name": "DavidIvorra",
        "rank": 46
      },
      {
        "wpm": 66.61,
        "acc": 98.52,
        "timestamp": 1781629655000,
        "raw": 66.61,
        "consistency": 72.89,
        "uid": "OixkPNCGunhnTNL0HQJaF5Eq1z83",
        "name": "reyhi",
        "rank": 47
      },
      {
        "wpm": 66.41,
        "acc": 94.05,
        "timestamp": 1781651699000,
        "raw": 66.41,
        "consistency": 65.3,
        "uid": "VxU6pxiZPBV2VQDFHVPoqKxl4qs1",
        "name": "vnado",
        "discordId": "356972666806337536",
        "discordAvatar": "fcb2dd44c500c30708ead7a424f37587",
        "rank": 48
      },
      {
        "wpm": 66.4,
        "acc": 94.15,
        "timestamp": 1781604496000,
        "raw": 68,
        "consistency": 65.15,
        "uid": "ICqsHj7G1QMkZPKPsJs7lPEqM3m1",
        "name": "victor_rodn13",
        "rank": 49
      },
      {
        "wpm": 63.81,
        "acc": 98.47,
        "timestamp": 1781645614000,
        "raw": 63.81,
        "consistency": 66.51,
        "uid": "ZFynFW0ex8bxKeivOdNBjAvofhj1",
        "name": "LukePizz",
        "rank": 50
      },
      {
        "wpm": 63.61,
        "acc": 96.45,
        "timestamp": 1781595343000,
        "raw": 66.81,
        "consistency": 70.84,
        "uid": "zpzJzKGe9aU8tCSzIiTndFfRMCk1",
        "name": "javisu",
        "rank": 51
      },
      {
        "wpm": 63.21,
        "acc": 89.32,
        "timestamp": 1781623595000,
        "raw": 64.61,
        "consistency": 56.93,
        "uid": "ove6e8Z2T0S1Q1XD261yKDTLN4L2",
        "name": "iv4nmc-tech",
        "rank": 52
      },
      {
        "wpm": 62.21,
        "acc": 95.14,
        "timestamp": 1781617188000,
        "raw": 63.01,
        "consistency": 72.25,
        "uid": "iCAKZ3Dfi7ZK857OzqcNjVNVxSa2",
        "name": "Omar1903920",
        "rank": 53
      },
      {
        "wpm": 61.79,
        "acc": 95.38,
        "timestamp": 1781574089000,
        "raw": 61.79,
        "consistency": 60.53,
        "uid": "tCsJKo0gvVUigmkhWfOCMVAbk6W2",
        "name": "Hernan_Lisio",
        "rank": 54
      },
      {
        "wpm": 58.6,
        "acc": 100,
        "timestamp": 1781604894000,
        "raw": 58.6,
        "consistency": 74.9,
        "uid": "tFv777LccbWvCpauq7FXoKniooE2",
        "name": "tonolmo",
        "discordId": "1205256344224010303",
        "discordAvatar": "2e27d6d90daaf9677bd4c45ecaa72eac",
        "rank": 55
      },
      {
        "wpm": 54.99,
        "acc": 94.83,
        "timestamp": 1781571770000,
        "raw": 54.99,
        "consistency": 70.22,
        "uid": "vnxTf2Dlnldla0Qe55fgOUTjp7m2",
        "name": "Luciano18",
        "rank": 56
      },
      {
        "wpm": 51.61,
        "acc": 92.01,
        "timestamp": 1781603443000,
        "raw": 54.81,
        "consistency": 65.4,
        "uid": "DNAHAKWmmNQZB1KkXX0lImC1DLr2",
        "name": "ivanchuu_88",
        "rank": 57
      },
      {
        "wpm": 46.81,
        "acc": 89.89,
        "timestamp": 1781590052000,
        "raw": 47.81,
        "consistency": 59.53,
        "uid": "QYdtPFlgRLh1nK65Sk9hU9qc4DG3",
        "name": "Andresowski",
        "rank": 58
      },
      {
        "wpm": 45.81,
        "acc": 85.04,
        "timestamp": 1781639823000,
        "raw": 72.21,
        "consistency": 68.11,
        "uid": "QIWRK9HNSQWrVU7DCaaZ9zgESOB2",
        "name": "EV54983",
        "discordId": "414445393342889984",
        "discordAvatar": "c915779c1650ed04c604c0cc801e7a1e",
        "rank": 59
      },
      {
        "wpm": 40.81,
        "acc": 94.59,
        "timestamp": 1781626803000,
        "raw": 41.81,
        "consistency": 29.75,
        "uid": "YCLApFKzZEhGkyK3zjTosb5cirs1",
        "name": "JhonMaycolTM",
        "rank": 60
      },
      {
        "wpm": 38.41,
        "acc": 99.48,
        "timestamp": 1781619409000,
        "raw": 38.41,
        "consistency": 67.35,
        "uid": "2Kwc8SfM26OEl0HmuoFo10Lf5Kz1",
        "name": "Charlie06",
        "rank": 61
      },
      {
        "wpm": 37.41,
        "acc": 87.98,
        "timestamp": 1781648224000,
        "raw": 42.01,
        "consistency": 48.19,
        "uid": "D3Dli995WRbuZD9RSHOVKvYPozI2",
        "name": "TheLuisMi",
        "rank": 62
      }
    ],
    "combinedEntryCount": 62
  },
  "pageSummaries": [
    {
      "page": 0,
      "url": "https://api.monkeytype.com/leaderboards/daily?pageSize=200&page=0&mode=time&language=spanish&daysBefore=1&mode2=%2260%22",
      "message": "Daily leaderboard retrieved",
      "reportedCount": 62,
      "reportedMinWpm": 37.41,
      "reportedPageSize": 200,
      "entriesFetched": 62
    },
    {
      "page": 1,
      "url": "https://api.monkeytype.com/leaderboards/daily?pageSize=200&page=1&mode=time&language=spanish&daysBefore=1&mode2=%2260%22",
      "message": "Daily leaderboard retrieved",
      "reportedCount": 62,
      "reportedMinWpm": 37.41,
      "reportedPageSize": 200,
      "entriesFetched": 0
    },
    {
      "page": 2,
      "url": "https://api.monkeytype.com/leaderboards/daily?pageSize=200&page=2&mode=time&language=spanish&daysBefore=1&mode2=%2260%22",
      "message": "Daily leaderboard retrieved",
      "reportedCount": 62,
      "reportedMinWpm": 37.41,
      "reportedPageSize": 200,
      "entriesFetched": 0
    },
    {
      "page": 3,
      "url": "https://api.monkeytype.com/leaderboards/daily?pageSize=200&page=3&mode=time&language=spanish&daysBefore=1&mode2=%2260%22",
      "message": "Daily leaderboard retrieved",
      "reportedCount": 62,
      "reportedMinWpm": 37.41,
      "reportedPageSize": 200,
      "entriesFetched": 0
    },
    {
      "page": 4,
      "url": "https://api.monkeytype.com/leaderboards/daily?pageSize=200&page=4&mode=time&language=spanish&daysBefore=1&mode2=%2260%22",
      "message": "Daily leaderboard retrieved",
      "reportedCount": 62,
      "reportedMinWpm": 37.41,
      "reportedPageSize": 200,
      "entriesFetched": 0
    }
  ]
}
