{
  "generatedAt": "2026-07-15T05:10:48.856Z",
  "leaderboardDate": "2026-07-14",
  "source": {
    "baseUrl": "https://api.monkeytype.com/leaderboards/daily",
    "sourceUrlTemplate": "https://api.monkeytype.com/leaderboards/daily?pageSize={pageSize}&page={page}&mode={mode}&mode2={jsonStringMode2}&language={language}&daysBefore={daysBefore}",
    "daysBefore": 1,
    "pageSize": 200,
    "mode": "time",
    "mode2": "15",
    "language": "italian",
    "pages": [
      0,
      1,
      2,
      3,
      4
    ]
  },
  "data": {
    "entries": [
      {
        "wpm": 173.6,
        "acc": 100,
        "timestamp": 1784017536000,
        "raw": 173.6,
        "consistency": 85.31,
        "uid": "Sk9u0R8AihR3PermdHyM0FqHtH12",
        "name": "Goxxa",
        "rank": 1
      },
      {
        "wpm": 165.38,
        "acc": 99.09,
        "timestamp": 1784021164000,
        "raw": 174.97,
        "consistency": 91.41,
        "uid": "uc1QJ9YqF3YHT1PpmieZlC7ElTh1",
        "name": "ipla",
        "rank": 2
      },
      {
        "wpm": 158.29,
        "acc": 95.77,
        "timestamp": 1784033061000,
        "raw": 170.29,
        "consistency": 89.97,
        "uid": "GMnGQ2uecKZiRtZp7khjZl1bQG42",
        "name": "Lmassabo",
        "rank": 3
      },
      {
        "wpm": 151.2,
        "acc": 100,
        "timestamp": 1784038182000,
        "raw": 151.2,
        "consistency": 91.91,
        "uid": "ggGExa189IV0QXSkGWu8gR1FN0z2",
        "name": "isederiso",
        "rank": 4
      },
      {
        "wpm": 151.2,
        "acc": 100,
        "timestamp": 1784039808000,
        "raw": 151.2,
        "consistency": 90.85,
        "uid": "QjPdxkZjVsNwS7IuwaYfDrarYYC2",
        "name": "pedwoo",
        "discordId": "701700348036775946",
        "discordAvatar": "5c2e7b5a70aaec00bae250b436511c9d",
        "rank": 5
      },
      {
        "wpm": 148,
        "acc": 98.45,
        "timestamp": 1784022475000,
        "raw": 154.4,
        "consistency": 85.48,
        "uid": "OTjPQ3GXDtdGtShXiSwSm6ZTqyq2",
        "name": "Dado_102",
        "rank": 6
      },
      {
        "wpm": 145.5,
        "acc": 100,
        "timestamp": 1784055520000,
        "raw": 145.5,
        "consistency": 86.93,
        "uid": "D0bQYTcBtdgD2nFZvY8jWNVWqxB3",
        "name": "Hardest",
        "rank": 7
      },
      {
        "wpm": 143.01,
        "acc": 100,
        "timestamp": 1784044875000,
        "raw": 143.01,
        "consistency": 84.26,
        "uid": "EWBJr84cDLWlCobRE4xv8L7YF563",
        "name": "Tonno",
        "rank": 8
      },
      {
        "wpm": 139.2,
        "acc": 100,
        "timestamp": 1784030889000,
        "raw": 139.2,
        "consistency": 86.72,
        "uid": "F5i3hcyFhuNn51tmrf3aNK2EaER2",
        "name": "danieleosx",
        "discordId": "847026169072844811",
        "discordAvatar": "4d2dca204074347d71aec1121275aab0",
        "rank": 9
      },
      {
        "wpm": 132,
        "acc": 95.53,
        "timestamp": 1784026229000,
        "raw": 132,
        "consistency": 73.6,
        "uid": "RNnm9pBaAgOYdD8ezpQ4lTCCjag2",
        "name": "Fungoh",
        "discordId": "611846448354557953",
        "discordAvatar": "55791b0d37736bc9d06da2427f1c0fa8",
        "rank": 10
      },
      {
        "wpm": 131.2,
        "acc": 99.39,
        "timestamp": 1784031479000,
        "raw": 131.2,
        "consistency": 83.74,
        "uid": "jMpzW2T7TxS8ruJWWGi6E7sdH4U2",
        "name": "Brvxx",
        "discordId": "480372770916663296",
        "discordAvatar": "ff5c6e2070282f20d8d4303e6ffc9805",
        "rank": 11
      },
      {
        "wpm": 131.11,
        "acc": 100,
        "timestamp": 1784021578000,
        "raw": 131.11,
        "consistency": 89.45,
        "uid": "c9VlsmDP7YQ2qTH7KjfiWicq7B23",
        "name": "typing_gandalf",
        "rank": 12
      },
      {
        "wpm": 129.6,
        "acc": 100,
        "timestamp": 1784050303000,
        "raw": 129.6,
        "consistency": 89.2,
        "uid": "3BMIp8iznQZxkIjb7Pevyo13ys33",
        "name": "Francy_18",
        "rank": 13
      },
      {
        "wpm": 128.8,
        "acc": 100,
        "timestamp": 1784049293000,
        "raw": 128.8,
        "consistency": 84.99,
        "uid": "uvIhrstzRBSACc50iKXfpDEBlzu1",
        "name": "MicroEconomist",
        "rank": 14
      },
      {
        "wpm": 128.71,
        "acc": 99.4,
        "timestamp": 1784056699000,
        "raw": 132.71,
        "consistency": 80.63,
        "uid": "P1y9R5jDzRTt4yCLW7wWkJYIktZ2",
        "name": "ilgigione",
        "rank": 15
      },
      {
        "wpm": 128,
        "acc": 100,
        "timestamp": 1784030782000,
        "raw": 128,
        "consistency": 86.02,
        "uid": "atRfngOf8iVcwYOvJknDPzPQWOg1",
        "name": "Macca315",
        "rank": 16
      },
      {
        "wpm": 127.2,
        "acc": 100,
        "timestamp": 1784018999000,
        "raw": 127.2,
        "consistency": 83.19,
        "uid": "t8LSFMg6U1OnAC0gDLaXQ0TzqcK2",
        "name": "bananaiogurt",
        "rank": 17
      },
      {
        "wpm": 125.6,
        "acc": 100,
        "timestamp": 1784060943000,
        "raw": 125.6,
        "consistency": 92.3,
        "uid": "lhKsgxBhhWceVTSncqeSCmHhsmm1",
        "name": "Paololimiti",
        "rank": 18
      },
      {
        "wpm": 125.6,
        "acc": 99.37,
        "timestamp": 1784048293000,
        "raw": 125.6,
        "consistency": 80.74,
        "uid": "ndSz4QdV7RSpmpk37kgyHtfZH7D3",
        "name": "Cioppo24",
        "rank": 19
      },
      {
        "wpm": 124,
        "acc": 100,
        "timestamp": 1784018472000,
        "raw": 124,
        "consistency": 87.93,
        "uid": "h4ymUIKPbldziBsElsJ2uJkV3Tz2",
        "name": "fmatt",
        "rank": 20
      },
      {
        "wpm": 122.32,
        "acc": 100,
        "timestamp": 1784013559000,
        "raw": 122.32,
        "consistency": 87.5,
        "uid": "5srJDT7J8fSFJu2RlzMdU61nJAy2",
        "name": "reminescenz",
        "rank": 21
      },
      {
        "wpm": 119.92,
        "acc": 98.73,
        "timestamp": 1784014543000,
        "raw": 126.32,
        "consistency": 90.92,
        "uid": "KviIEJpfLeWE7uwqlwQJzyzznSp1",
        "name": "Snipercat",
        "rank": 22
      },
      {
        "wpm": 118.32,
        "acc": 100,
        "timestamp": 1784047148000,
        "raw": 118.32,
        "consistency": 86.73,
        "uid": "cN6agueQImdmVqNdtIUBU7Je3Pk1",
        "name": "pastasugo89",
        "rank": 23
      },
      {
        "wpm": 116.72,
        "acc": 95.57,
        "timestamp": 1784041664000,
        "raw": 123.92,
        "consistency": 84.16,
        "uid": "xbPxobM8CvSxLn6EGvw2n6YypYX2",
        "name": "domenicobonali",
        "rank": 24
      },
      {
        "wpm": 115.05,
        "acc": 95.45,
        "timestamp": 1784045536000,
        "raw": 121.44,
        "consistency": 85.14,
        "uid": "QL4dLaqaIabjnqGqKKfDTshw0W23",
        "name": "E1ES",
        "rank": 25
      },
      {
        "wpm": 110.25,
        "acc": 99.28,
        "timestamp": 1784033535000,
        "raw": 110.25,
        "consistency": 79.35,
        "uid": "RRndyoEJ7FOtbEuFG8pj2SMKizw1",
        "name": "Sangallone",
        "discordId": "1010182347255193690",
        "discordAvatar": "d46754991d39e416f4eaeee9ba588967",
        "rank": 26
      },
      {
        "wpm": 106.4,
        "acc": 89.33,
        "timestamp": 1784019964000,
        "raw": 109.6,
        "consistency": 56.68,
        "uid": "r8LI0O6jCAN63mTi0FoDKjJfrJp2",
        "name": "AeNigma",
        "rank": 27
      },
      {
        "wpm": 106.26,
        "acc": 100,
        "timestamp": 1784032955000,
        "raw": 106.26,
        "consistency": 88.45,
        "uid": "eFPHZVGkcXT2iTu26mGNzVJuVOI3",
        "name": "ponziopluto",
        "rank": 28
      },
      {
        "wpm": 105.6,
        "acc": 87.08,
        "timestamp": 1784073585000,
        "raw": 142.4,
        "consistency": 81.57,
        "uid": "fY4M9KoTJuQ63A2km0c7Ppij8Ir2",
        "name": "foggytypes",
        "discordId": "375290241298464768",
        "discordAvatar": "b2f478628f4854bb76ff9f204acf0e9b",
        "rank": 29
      },
      {
        "wpm": 104.8,
        "acc": 97.78,
        "timestamp": 1784043426000,
        "raw": 104.8,
        "consistency": 84.29,
        "uid": "BFukRN6PMlZnFWAUzacvRiBDeg82",
        "name": "Carmine005",
        "rank": 30
      },
      {
        "wpm": 103.93,
        "acc": 98.54,
        "timestamp": 1784011466000,
        "raw": 108.73,
        "consistency": 75.4,
        "uid": "5tOjCMXfVzQpDJ3oxbOZ4yk4mf72",
        "name": "mtyperthesheriff",
        "rank": 31
      },
      {
        "wpm": 103.13,
        "acc": 91.57,
        "timestamp": 1784070444000,
        "raw": 131.91,
        "consistency": 83.68,
        "uid": "4EsrPFijwsVXeqT1qoYcSWyq2wo2",
        "name": "basedbased",
        "rank": 32
      },
      {
        "wpm": 102.4,
        "acc": 100,
        "timestamp": 1784047286000,
        "raw": 102.4,
        "consistency": 79.1,
        "uid": "ny5N2SvCJfUvxrKR1j8yXGgoEgJ2",
        "name": "_leo_",
        "rank": 33
      },
      {
        "wpm": 100.73,
        "acc": 100,
        "timestamp": 1784028860000,
        "raw": 100.73,
        "consistency": 79.24,
        "uid": "VCbwjAFn3aR99MsmrbpO02s3Tm92",
        "name": "monkeydoodle444",
        "rank": 34
      },
      {
        "wpm": 100,
        "acc": 89.58,
        "timestamp": 1784015903000,
        "raw": 104,
        "consistency": 73.98,
        "uid": "Exs2joU790PwsFO3ZGD4Aocow6d2",
        "name": "SaturnIsBad",
        "rank": 35
      },
      {
        "wpm": 99.93,
        "acc": 97.66,
        "timestamp": 1784026794000,
        "raw": 99.93,
        "consistency": 75.85,
        "uid": "Hsy47NUsQPOOvg2ROgxlobvXwMc2",
        "name": "Xandre03",
        "rank": 36
      },
      {
        "wpm": 98.33,
        "acc": 98.45,
        "timestamp": 1784036902000,
        "raw": 103.13,
        "consistency": 77.61,
        "uid": "efwH2vxYYjT7JfaixCPiLRgqJEn2",
        "name": "Andre3393",
        "rank": 37
      },
      {
        "wpm": 97.6,
        "acc": 95.35,
        "timestamp": 1784026547000,
        "raw": 97.6,
        "consistency": 67.45,
        "uid": "TOYtWfOisXSYITrKMqVK5dOXz3F2",
        "name": "lilscipio",
        "rank": 38
      },
      {
        "wpm": 95.2,
        "acc": 95.28,
        "timestamp": 1784018091000,
        "raw": 99.2,
        "consistency": 65.01,
        "uid": "g40EP4rrhzUBu7MKHGv8mCkprx03",
        "name": "biagnic",
        "rank": 39
      },
      {
        "wpm": 95.14,
        "acc": 100,
        "timestamp": 1784042270000,
        "raw": 95.14,
        "consistency": 85.42,
        "uid": "uUf96xfjcpQYQn5JYD1Hn0Q0nn43",
        "name": "danieledd",
        "rank": 40
      },
      {
        "wpm": 94.4,
        "acc": 99.16,
        "timestamp": 1784038453000,
        "raw": 94.4,
        "consistency": 80.76,
        "uid": "xyxtYwk02SMACjwRT9GMYxejLuW2",
        "name": "sebzav",
        "rank": 41
      },
      {
        "wpm": 94.4,
        "acc": 96.72,
        "timestamp": 1784044576000,
        "raw": 94.4,
        "consistency": 75.88,
        "uid": "BqpZa2rwwBeiOVJLpDuLyNBFUbT2",
        "name": "Patawak0",
        "rank": 42
      },
      {
        "wpm": 94.34,
        "acc": 96.03,
        "timestamp": 1784029599000,
        "raw": 94.34,
        "consistency": 64.22,
        "uid": "0eoQQ6vvOnXiwDChAlrvWKnikvs1",
        "name": "n1am",
        "rank": 43
      },
      {
        "wpm": 93.6,
        "acc": 100,
        "timestamp": 1784028546000,
        "raw": 93.6,
        "consistency": 82.36,
        "uid": "hQsg1Yd8LDg8FG2p3vNYxUpZmdk2",
        "name": "itzDanjeo",
        "rank": 44
      },
      {
        "wpm": 93.6,
        "acc": 100,
        "timestamp": 1784036328000,
        "raw": 93.6,
        "consistency": 90.41,
        "uid": "IFtAO0Zct4OXjx2Fof0WfNU3DpQ2",
        "name": "jervasone",
        "rank": 45
      },
      {
        "wpm": 92,
        "acc": 100,
        "timestamp": 1784041227000,
        "raw": 92,
        "consistency": 90.88,
        "uid": "o3jreoaM9dZvdaU6oaUzuXl8NFQ2",
        "name": "loris98",
        "rank": 46
      },
      {
        "wpm": 89.54,
        "acc": 96.55,
        "timestamp": 1784022087000,
        "raw": 89.54,
        "consistency": 80.84,
        "uid": "NYLAjxSor0UVcyQYXTLmk6VjHzs1",
        "name": "batti",
        "rank": 47
      },
      {
        "wpm": 87.2,
        "acc": 86.71,
        "timestamp": 1784056825000,
        "raw": 104.8,
        "consistency": 74.92,
        "uid": "FPV5TrnCG1d4n9R41KwrKEpRaRB3",
        "name": "Gabricorei9",
        "discordId": "702399762812633189",
        "discordAvatar": "b4bd8f9dce93d57fd26993876bcc7070",
        "rank": 48
      },
      {
        "wpm": 83.78,
        "acc": 96.33,
        "timestamp": 1784041726000,
        "raw": 83.78,
        "consistency": 79,
        "uid": "OQdnvB8dwKSnajSR9dz6UAUqROz2",
        "name": "Lime004",
        "rank": 49
      },
      {
        "wpm": 83.14,
        "acc": 100,
        "timestamp": 1784054084000,
        "raw": 83.14,
        "consistency": 86.61,
        "uid": "ouUu4CDa1oVIWrCKEAFVjspqwLm2",
        "name": "ArcVv",
        "rank": 50
      },
      {
        "wpm": 82.4,
        "acc": 95.45,
        "timestamp": 1784022272000,
        "raw": 87.2,
        "consistency": 82.99,
        "uid": "mMlbGH9XN5OaJ3IatcqhgaK4PMH2",
        "name": "thex_types",
        "rank": 51
      },
      {
        "wpm": 81.49,
        "acc": 86.13,
        "timestamp": 1784022166000,
        "raw": 109.45,
        "consistency": 80.88,
        "uid": "NsiRNkQjv9hribg5vyKss4UJjI93",
        "name": "thevenny",
        "discordId": "667099151464398893",
        "discordAvatar": "61b25a00b1e202a3d4e8a540b7ed6aa0",
        "rank": 52
      },
      {
        "wpm": 80.75,
        "acc": 97.17,
        "timestamp": 1784045953000,
        "raw": 83.94,
        "consistency": 74.44,
        "uid": "7OFxHfYzwjU6FaU3qNOKh5qMa9i2",
        "name": "Nullname0x00",
        "rank": 53
      },
      {
        "wpm": 76.7,
        "acc": 93.58,
        "timestamp": 1784051487000,
        "raw": 83.09,
        "consistency": 70.5,
        "uid": "hWeW1GbfYCZubH03BXELK8vOygt1",
        "name": "siriorigel",
        "rank": 54
      },
      {
        "wpm": 72.8,
        "acc": 96.08,
        "timestamp": 1784048439000,
        "raw": 79.2,
        "consistency": 68.6,
        "uid": "HYstTqAr1MTZBykWUr3EFqHD4Om2",
        "name": "Volperix",
        "rank": 55
      },
      {
        "wpm": 68.75,
        "acc": 95.88,
        "timestamp": 1784034228000,
        "raw": 75.15,
        "consistency": 73.6,
        "uid": "FO1GNMnO7ehwzZ5vwB5YfQYkeYk2",
        "name": "sebinonino",
        "rank": 56
      },
      {
        "wpm": 61.6,
        "acc": 94.38,
        "timestamp": 1784072687000,
        "raw": 68,
        "consistency": 68.95,
        "uid": "eGHLZIL6D5OjLyErbn9HvFrmmht1",
        "name": "faelrano",
        "rank": 57
      },
      {
        "wpm": 60,
        "acc": 91.46,
        "timestamp": 1784037902000,
        "raw": 60,
        "consistency": 70.99,
        "uid": "6CBftyRKNdWZ3pBYvOK7MHHggqu1",
        "name": "JDMSB",
        "rank": 58
      },
      {
        "wpm": 55.96,
        "acc": 100,
        "timestamp": 1784021049000,
        "raw": 55.96,
        "consistency": 83.1,
        "uid": "Xe6OBbUvSIfgZv8kUPm9WWfcL0v1",
        "name": "FilippoRo",
        "rank": 59
      },
      {
        "wpm": 55.96,
        "acc": 91.86,
        "timestamp": 1784071831000,
        "raw": 64.76,
        "consistency": 71.19,
        "uid": "METH9TVETDQxdCQgG6mTWg2bZ3z1",
        "name": "neofelis9690",
        "rank": 60
      },
      {
        "wpm": 44.77,
        "acc": 93.44,
        "timestamp": 1784049411000,
        "raw": 44.77,
        "consistency": 72.38,
        "uid": "SJxbUY4NJ5PUqztzI3OQA8TRz4o1",
        "name": "Ghetti",
        "rank": 61
      }
    ],
    "combinedEntryCount": 61
  },
  "pageSummaries": [
    {
      "page": 0,
      "url": "https://api.monkeytype.com/leaderboards/daily?pageSize=200&page=0&mode=time&language=italian&daysBefore=1&mode2=%2215%22",
      "message": "Daily leaderboard retrieved",
      "reportedCount": 61,
      "reportedMinWpm": 44.77,
      "reportedPageSize": 200,
      "entriesFetched": 61
    },
    {
      "page": 1,
      "url": "https://api.monkeytype.com/leaderboards/daily?pageSize=200&page=1&mode=time&language=italian&daysBefore=1&mode2=%2215%22",
      "message": "Daily leaderboard retrieved",
      "reportedCount": 61,
      "reportedMinWpm": 44.77,
      "reportedPageSize": 200,
      "entriesFetched": 0
    },
    {
      "page": 2,
      "url": "https://api.monkeytype.com/leaderboards/daily?pageSize=200&page=2&mode=time&language=italian&daysBefore=1&mode2=%2215%22",
      "message": "Daily leaderboard retrieved",
      "reportedCount": 61,
      "reportedMinWpm": 44.77,
      "reportedPageSize": 200,
      "entriesFetched": 0
    },
    {
      "page": 3,
      "url": "https://api.monkeytype.com/leaderboards/daily?pageSize=200&page=3&mode=time&language=italian&daysBefore=1&mode2=%2215%22",
      "message": "Daily leaderboard retrieved",
      "reportedCount": 61,
      "reportedMinWpm": 44.77,
      "reportedPageSize": 200,
      "entriesFetched": 0
    },
    {
      "page": 4,
      "url": "https://api.monkeytype.com/leaderboards/daily?pageSize=200&page=4&mode=time&language=italian&daysBefore=1&mode2=%2215%22",
      "message": "Daily leaderboard retrieved",
      "reportedCount": 61,
      "reportedMinWpm": 44.77,
      "reportedPageSize": 200,
      "entriesFetched": 0
    }
  ]
}
