{
  "generatedAt": "2026-07-16T05:21:33.972Z",
  "leaderboardDate": "2026-07-15",
  "source": {
    "baseUrl": "https://api.monkeytype.com/leaderboards/daily",
    "sourceUrlTemplate": "https://api.monkeytype.com/leaderboards/daily?pageSize={pageSize}&page={page}&mode={mode}&mode2={jsonStringMode2}&language={language}&daysBefore={daysBefore}",
    "daysBefore": 1,
    "pageSize": 200,
    "mode": "time",
    "mode2": "60",
    "language": "spanish",
    "pages": [
      0,
      1,
      2,
      3,
      4
    ]
  },
  "data": {
    "entries": [
      {
        "wpm": 147.98,
        "acc": 94.81,
        "timestamp": 1784080144000,
        "raw": 159.57,
        "consistency": 78.1,
        "uid": "d6BDlP2Qs2bPPwhZVqzFiNeXNbZ2",
        "name": "JoshielG",
        "rank": 1
      },
      {
        "wpm": 141.38,
        "acc": 95.93,
        "timestamp": 1784149571000,
        "raw": 147.98,
        "consistency": 78.44,
        "uid": "7hhc7Lg6VUR6Ith6I8zEQIoTSAc2",
        "name": "derivamdc",
        "rank": 2
      },
      {
        "wpm": 134.98,
        "acc": 99.42,
        "timestamp": 1784102186000,
        "raw": 137.78,
        "consistency": 88.72,
        "uid": "pUza4KLY1SeinwrcvVkojria0492",
        "name": "sanrafael",
        "rank": 3
      },
      {
        "wpm": 127.2,
        "acc": 98.92,
        "timestamp": 1784103209000,
        "raw": 128.4,
        "consistency": 79.82,
        "uid": "NxqVqJif1rTKVPUqA92kfQvrIG82",
        "name": "kizp",
        "discordId": "820057948264333352",
        "discordAvatar": "27f5e82d48b4ff503275094145dcf610",
        "badgeId": 12,
        "rank": 4
      },
      {
        "wpm": 121.14,
        "acc": 97.62,
        "timestamp": 1784133370000,
        "raw": 121.14,
        "consistency": 73.58,
        "uid": "1vnTFwMZ6cfTnAuXhRArnbuEBMy1",
        "name": "Maru",
        "discordId": "178588508468805632",
        "discordAvatar": "3ae202ed3e650e62f765425c898acaaa",
        "rank": 5
      },
      {
        "wpm": 116.8,
        "acc": 98.16,
        "timestamp": 1784136141000,
        "raw": 118,
        "consistency": 76.33,
        "uid": "OrbL9z1RsMXq0ilByvRMWxBwvin2",
        "name": "HawkenG",
        "rank": 6
      },
      {
        "wpm": 116.8,
        "acc": 95.6,
        "timestamp": 1784139884000,
        "raw": 128.8,
        "consistency": 73.96,
        "uid": "Ah2veIGoFQabsGLkEJOT3hJzygv1",
        "name": "Socramyos",
        "discordId": "627557954907799552",
        "discordAvatar": "e95034d6910ebb596638b36ebb69c8d0",
        "rank": 7
      },
      {
        "wpm": 115.78,
        "acc": 99.49,
        "timestamp": 1784136063000,
        "raw": 118.78,
        "consistency": 83.37,
        "uid": "YRRsst8HgNNix9L6DBgICkLRIhO2",
        "name": "DebraT",
        "rank": 8
      },
      {
        "wpm": 113.4,
        "acc": 98.29,
        "timestamp": 1784124029000,
        "raw": 113.4,
        "consistency": 75.25,
        "uid": "dNv1u1Jy9AVFrTQJaf0zhpNj2OG3",
        "name": "Alfafuentes",
        "rank": 9
      },
      {
        "wpm": 111.6,
        "acc": 98.77,
        "timestamp": 1784159976000,
        "raw": 113.2,
        "consistency": 80.77,
        "uid": "kwGEAtkPzGa5S6wVVnfjMQteh5x1",
        "name": "monocito_",
        "discordId": "834620052984692788",
        "discordAvatar": "721f1e97e1afccb258dba2868723bf81",
        "badgeId": 14,
        "rank": 10
      },
      {
        "wpm": 110.58,
        "acc": 98.43,
        "timestamp": 1784108820000,
        "raw": 114.98,
        "consistency": 85.83,
        "uid": "wXRkBEEkPCf5AKKHgChLzpJWsR52",
        "name": "Tuccini98",
        "rank": 11
      },
      {
        "wpm": 108.18,
        "acc": 94.75,
        "timestamp": 1784123369000,
        "raw": 121.78,
        "consistency": 86.44,
        "uid": "2iAOMue9aoRDrSKPf78bwdq4jhw2",
        "name": "frostbitntest",
        "rank": 12
      },
      {
        "wpm": 106.15,
        "acc": 97.61,
        "timestamp": 1784159679000,
        "raw": 106.15,
        "consistency": 75.6,
        "uid": "U1K0sS76rtguTuFk8a71jce80MM2",
        "name": "gatouski",
        "discordId": "1217313341501079564",
        "discordAvatar": "6306e97774556aad147683bba462f82c",
        "rank": 13
      },
      {
        "wpm": 103.38,
        "acc": 98.66,
        "timestamp": 1784088519000,
        "raw": 103.38,
        "consistency": 79.11,
        "uid": "uyCBzWlsymV0zcBFpB8cYndlBhx1",
        "name": "GambitoParadox",
        "discordId": "1214662526609002576",
        "discordAvatar": "9596bcddfb2e7ad9f4d2e77c86a6e153",
        "rank": 14
      },
      {
        "wpm": 103.37,
        "acc": 99.05,
        "timestamp": 1784116118000,
        "raw": 104.57,
        "consistency": 78.79,
        "uid": "9UgoMVtlcabyVrAnBW1Z9JpRxOi1",
        "name": "UnicornioMilitar",
        "discordId": "193099751577747457",
        "discordAvatar": "90de27501db0c4c3e46248d133b93861",
        "rank": 15
      },
      {
        "wpm": 102.38,
        "acc": 86.12,
        "timestamp": 1784111660000,
        "raw": 145.38,
        "consistency": 78.84,
        "uid": "A6Gkj4RXcJbkjhta0yLlaZFvwWQ2",
        "name": "carlostato",
        "rank": 16
      },
      {
        "wpm": 102.18,
        "acc": 98.84,
        "timestamp": 1784123755000,
        "raw": 102.18,
        "consistency": 81.16,
        "uid": "h4kElN8TOUb9UDKrBcRWzdvwFm12",
        "name": "chacon",
        "rank": 17
      },
      {
        "wpm": 101.38,
        "acc": 96.12,
        "timestamp": 1784153658000,
        "raw": 105.98,
        "consistency": 81.28,
        "uid": "yfQYLVQ51aSCZ6QqFDzvFQMSH1B3",
        "name": "Jesuswag",
        "discordId": "470331227208024079",
        "discordAvatar": "97334760bd0cc6f338d3731fe3a59983",
        "rank": 18
      },
      {
        "wpm": 101.2,
        "acc": 97.35,
        "timestamp": 1784124790000,
        "raw": 101.4,
        "consistency": 71.12,
        "uid": "owhTdxQyxJTpLqMxXwYLCZbRBFB3",
        "name": "ThatNova",
        "discordId": "333864887434346497",
        "discordAvatar": "9b39fb8023bc698e66802c1444a14453",
        "rank": 19
      },
      {
        "wpm": 100.78,
        "acc": 97.5,
        "timestamp": 1784135735000,
        "raw": 100.78,
        "consistency": 69.58,
        "uid": "j9ZYL04TQFVeBxRFN1U1quZ71Vx2",
        "name": "Bplayb",
        "rank": 20
      },
      {
        "wpm": 100.58,
        "acc": 95.84,
        "timestamp": 1784157464000,
        "raw": 100.58,
        "consistency": 73.28,
        "uid": "zxuR4k9tNbdu0VevMW09AnRzxcM2",
        "name": "supa369",
        "rank": 21
      },
      {
        "wpm": 98.38,
        "acc": 97.82,
        "timestamp": 1784126884000,
        "raw": 98.38,
        "consistency": 74.82,
        "uid": "cgpz60mYCCZqL4FMfJusoT4XOSa2",
        "name": "Sh1bo0",
        "discordId": "569337096062500864",
        "discordAvatar": "f3bd00e6ff445b57c9a6bbe805c1ff3e",
        "rank": 22
      },
      {
        "wpm": 97,
        "acc": 92.61,
        "timestamp": 1784111324000,
        "raw": 106.2,
        "consistency": 74.35,
        "uid": "a47I0P7SMDeWJ4yhNrDfSRkj3m22",
        "name": "Kiliar",
        "rank": 23
      },
      {
        "wpm": 94.78,
        "acc": 95.56,
        "timestamp": 1784153414000,
        "raw": 102.38,
        "consistency": 76.55,
        "uid": "2IAWW1s9r2hi7tH7koCG4fcfrz73",
        "name": "frncchiappe",
        "rank": 24
      },
      {
        "wpm": 94.18,
        "acc": 98.34,
        "timestamp": 1784157699000,
        "raw": 94.18,
        "consistency": 75,
        "uid": "2NeJODQIoXcUXSTJYCh7tefJyBk2",
        "name": "tangarine09",
        "rank": 25
      },
      {
        "wpm": 93.58,
        "acc": 96.12,
        "timestamp": 1784136876000,
        "raw": 95.38,
        "consistency": 75.7,
        "uid": "UfffWx0kreMz4YcNDgtd4pbInLq2",
        "name": "mcalejandro",
        "rank": 26
      },
      {
        "wpm": 91.75,
        "acc": 94.95,
        "timestamp": 1784086457000,
        "raw": 92.75,
        "consistency": 67.13,
        "uid": "894BEjske3TQmvwmkY17EW5S2KI2",
        "name": "angelJavier",
        "discordId": "1461272561299226717",
        "rank": 27
      },
      {
        "wpm": 88.99,
        "acc": 95.72,
        "timestamp": 1784154485000,
        "raw": 89.79,
        "consistency": 74.4,
        "uid": "hmJ920V494Ylr4Uy426RM7qZElv2",
        "name": "Felipon2025",
        "rank": 28
      },
      {
        "wpm": 88.99,
        "acc": 91.76,
        "timestamp": 1784114308000,
        "raw": 107.38,
        "consistency": 69.93,
        "uid": "pG1buFkSHRRk2XQSYHtcYeaEsAI3",
        "name": "k4ppax",
        "rank": 29
      },
      {
        "wpm": 86.8,
        "acc": 94.06,
        "timestamp": 1784088211000,
        "raw": 94,
        "consistency": 78.65,
        "uid": "j8OpNGsBYJXQYUyjthtHPbidSHu1",
        "name": "KOCHO-SAN",
        "rank": 30
      },
      {
        "wpm": 86.39,
        "acc": 96.05,
        "timestamp": 1784158934000,
        "raw": 86.39,
        "consistency": 66.88,
        "uid": "OzYazg2jEkZ9RmeKCZp0fUgtTUP2",
        "name": "LDAC-007",
        "rank": 31
      },
      {
        "wpm": 85.4,
        "acc": 96.61,
        "timestamp": 1784138139000,
        "raw": 85.4,
        "consistency": 75.22,
        "uid": "RRlUVQnw7oVkAiRNRbysUe6TW232",
        "name": "typer007",
        "discordId": "710887321570115615",
        "discordAvatar": "bdb90291c3db064e4af80bc9298254b2",
        "rank": 32
      },
      {
        "wpm": 85.19,
        "acc": 98.85,
        "timestamp": 1784075840000,
        "raw": 85.19,
        "consistency": 75.84,
        "uid": "c5im9E3Cz7Sgeo1xgFvZduh2tdF2",
        "name": "Fish_Alone",
        "discordId": "943559761184579595",
        "discordAvatar": "18196683465e0f22461f7658661eb430",
        "rank": 33
      },
      {
        "wpm": 85.19,
        "acc": 98.16,
        "timestamp": 1784144962000,
        "raw": 85.19,
        "consistency": 72.54,
        "uid": "VaJ6oa3oaHRrkVGsPRhvY2Vxp7C3",
        "name": "dperico",
        "rank": 34
      },
      {
        "wpm": 84.8,
        "acc": 94.67,
        "timestamp": 1784142018000,
        "raw": 84.8,
        "consistency": 69.55,
        "uid": "EwzUcmgFI3QX60C9qLKD8C9ksbF3",
        "name": "bad_gamerUWU",
        "discordId": "532074329886818306",
        "discordAvatar": "3cb9bf07845b74066289441ba432da40",
        "rank": 35
      },
      {
        "wpm": 83.2,
        "acc": 97.67,
        "timestamp": 1784118066000,
        "raw": 83.2,
        "consistency": 73.98,
        "uid": "nwtw43l2a5gF17UGMX0ClvttLHe2",
        "name": "janoantelo",
        "rank": 36
      },
      {
        "wpm": 83.17,
        "acc": 95.92,
        "timestamp": 1784148548000,
        "raw": 84.37,
        "consistency": 68.8,
        "uid": "44Ryarrn5gRokiySwxHAKmp78vy2",
        "name": "RoroRaa",
        "rank": 37
      },
      {
        "wpm": 82.6,
        "acc": 95.64,
        "timestamp": 1784141637000,
        "raw": 82.6,
        "consistency": 69.25,
        "uid": "wNGFqTxsqSb0ci6GAEmnRbkmgLr2",
        "name": "Pain__",
        "discordId": "383110106570555392",
        "discordAvatar": "d192904e76fd2a3e05cd6a3677e1353c",
        "rank": 38
      },
      {
        "wpm": 80.57,
        "acc": 93.85,
        "timestamp": 1784080587000,
        "raw": 93.77,
        "consistency": 71.28,
        "uid": "GHRgwU3LaXZbrmIQ11LvkZqc4Ca2",
        "name": "monkechad729",
        "discordId": "825422360856494091",
        "discordAvatar": "1c5532fa2c9f6f494c11fc42d972710a",
        "rank": 39
      },
      {
        "wpm": 80.19,
        "acc": 98.31,
        "timestamp": 1784130468000,
        "raw": 81.39,
        "consistency": 71.05,
        "uid": "X68mt8wlfMeWzHx9D995myANed43",
        "name": "jakuri",
        "rank": 40
      },
      {
        "wpm": 79,
        "acc": 96.01,
        "timestamp": 1784155759000,
        "raw": 82.8,
        "consistency": 74.58,
        "uid": "goZSmMHMusedn4utRg0FeT2oNNO2",
        "name": "Walesp",
        "rank": 41
      },
      {
        "wpm": 77.37,
        "acc": 98.29,
        "timestamp": 1784139753000,
        "raw": 81.97,
        "consistency": 84.38,
        "uid": "nTpUBmoRzaWEO2JdeE0TSEoHW5V2",
        "name": "tata02",
        "rank": 42
      },
      {
        "wpm": 77.17,
        "acc": 90.99,
        "timestamp": 1784134548000,
        "raw": 90.97,
        "consistency": 66.32,
        "uid": "JfM4ccFr72O2uxePKybzN9L8mMO2",
        "name": "ksszx",
        "rank": 43
      },
      {
        "wpm": 76.2,
        "acc": 96.22,
        "timestamp": 1784155547000,
        "raw": 76.2,
        "consistency": 75.62,
        "uid": "eUFK1lCl3tZoNCeY8k2zBggTZ5O2",
        "name": "Valenti_73",
        "rank": 44
      },
      {
        "wpm": 75,
        "acc": 94.95,
        "timestamp": 1784132653000,
        "raw": 75,
        "consistency": 68.2,
        "uid": "Efiz7jUiKtXVxUdGLnrrhW3ZQvE3",
        "name": "David72",
        "rank": 45
      },
      {
        "wpm": 74.79,
        "acc": 96.89,
        "timestamp": 1784101918000,
        "raw": 74.79,
        "consistency": 64.44,
        "uid": "9ud09tTpg8QfH0oJObY2vLA08n23",
        "name": "Pinchin",
        "rank": 46
      },
      {
        "wpm": 74.6,
        "acc": 91.93,
        "timestamp": 1784128413000,
        "raw": 74.6,
        "consistency": 69.65,
        "uid": "Xmb7p1XSTxOr86lngdqvWnhTSAE2",
        "name": "vladysluv",
        "discordId": "736952610476785695",
        "discordAvatar": "191b44fdac7c841359c9649f587082e8",
        "rank": 47
      },
      {
        "wpm": 74.19,
        "acc": 94.88,
        "timestamp": 1784081735000,
        "raw": 74.19,
        "consistency": 51.52,
        "uid": "XfGjbGX4PqOxx2NyDAM4fYFqQLp1",
        "name": "Brayan_csk",
        "rank": 48
      },
      {
        "wpm": 72.59,
        "acc": 97.34,
        "timestamp": 1784150334000,
        "raw": 72.59,
        "consistency": 66.81,
        "uid": "SoO84RYjZkhjcUCS6dXtM6sMV4h1",
        "name": "lcsolano",
        "rank": 49
      },
      {
        "wpm": 72.19,
        "acc": 96.31,
        "timestamp": 1784081024000,
        "raw": 72.19,
        "consistency": 68.94,
        "uid": "fj3Ym483TMU9S0lpe121PXZzYHo2",
        "name": "Anarkemos",
        "rank": 50
      },
      {
        "wpm": 71.4,
        "acc": 97.28,
        "timestamp": 1784122567000,
        "raw": 71.4,
        "consistency": 65.83,
        "uid": "xttcombzcvSFJTqk1K94J0KEyfx1",
        "name": "imhector",
        "discordId": "660545636327751711",
        "discordAvatar": "5de58aa3726aa5e1fc832691f68070f7",
        "rank": 51
      },
      {
        "wpm": 71.19,
        "acc": 96.24,
        "timestamp": 1784129973000,
        "raw": 71.19,
        "consistency": 64.21,
        "uid": "MkcB8vp8oGPsqF8oBFFTkRE58683",
        "name": "LANKLIBRE56",
        "discordId": "655887224977489922",
        "rank": 52
      },
      {
        "wpm": 70.4,
        "acc": 98.61,
        "timestamp": 1784149744000,
        "raw": 70.4,
        "consistency": 73.83,
        "uid": "GdgM2sWN60QEsNjKmxYyaMcbNkV2",
        "name": "capmaravilla",
        "rank": 53
      },
      {
        "wpm": 69.6,
        "acc": 97.49,
        "timestamp": 1784136619000,
        "raw": 69.6,
        "consistency": 72.63,
        "uid": "OixkPNCGunhnTNL0HQJaF5Eq1z83",
        "name": "reyhi",
        "rank": 54
      },
      {
        "wpm": 67.19,
        "acc": 97.39,
        "timestamp": 1784154917000,
        "raw": 67.19,
        "consistency": 73.51,
        "uid": "NpU7pnZzBpelOCntCMePz3ylZ8A2",
        "name": "EmerM",
        "rank": 55
      },
      {
        "wpm": 64.19,
        "acc": 99.38,
        "timestamp": 1784155494000,
        "raw": 64.19,
        "consistency": 65.24,
        "uid": "kfU9jTq2pdVVhQgm1pcUg91NyLE2",
        "name": "jsilvaf",
        "rank": 56
      },
      {
        "wpm": 63.59,
        "acc": 89.21,
        "timestamp": 1784098096000,
        "raw": 81.99,
        "consistency": 74.34,
        "uid": "9lxjl5kR9HbKst4jSc8cujr40uO2",
        "name": "DavidIvorra",
        "rank": 57
      },
      {
        "wpm": 63.19,
        "acc": 93.37,
        "timestamp": 1784086516000,
        "raw": 70.79,
        "consistency": 68.56,
        "uid": "NS0NtxmI9FXQtbWUnVllS3y35bm1",
        "name": "Aletheia07",
        "discordId": "646904470516531201",
        "discordAvatar": "ad10a071cb3b75d762953b690f2fbdf4",
        "rank": 58
      },
      {
        "wpm": 61.6,
        "acc": 93.71,
        "timestamp": 1784110498000,
        "raw": 61.6,
        "consistency": 65.24,
        "uid": "EVd5kYAWy9PqXfeVTk5BVPZ5mXD3",
        "name": "lucaspy7",
        "rank": 59
      },
      {
        "wpm": 60.99,
        "acc": 89.9,
        "timestamp": 1784142961000,
        "raw": 77.39,
        "consistency": 63.48,
        "uid": "QIWRK9HNSQWrVU7DCaaZ9zgESOB2",
        "name": "EV54983",
        "discordId": "414445393342889984",
        "discordAvatar": "c915779c1650ed04c604c0cc801e7a1e",
        "badgeId": 9,
        "rank": 60
      },
      {
        "wpm": 59.6,
        "acc": 90.36,
        "timestamp": 1784095209000,
        "raw": 59.6,
        "consistency": 72.7,
        "uid": "DmvooSg766hnT43OdnmreoQPhat1",
        "name": "CrXs",
        "rank": 61
      },
      {
        "wpm": 58.59,
        "acc": 93.98,
        "timestamp": 1784106990000,
        "raw": 63.19,
        "consistency": 74.77,
        "uid": "wkkBPDmxKQe16PDMHCvDUeZbNrp1",
        "name": "Sarth4k",
        "discordId": "707115699344244757",
        "discordAvatar": "942f52425d96d9c6c5eeeeb94c56b87d",
        "rank": 62
      },
      {
        "wpm": 55.4,
        "acc": 96.05,
        "timestamp": 1784114056000,
        "raw": 58.4,
        "consistency": 67.6,
        "uid": "ICqsHj7G1QMkZPKPsJs7lPEqM3m1",
        "name": "victor_rodn13",
        "rank": 63
      },
      {
        "wpm": 54.79,
        "acc": 91.69,
        "timestamp": 1784146420000,
        "raw": 54.79,
        "consistency": 48.22,
        "uid": "OqhxQlMv9TZhHWpMrgSNthc11lg1",
        "name": "from95til",
        "rank": 64
      },
      {
        "wpm": 53.99,
        "acc": 92.02,
        "timestamp": 1784110698000,
        "raw": 63.19,
        "consistency": 69.88,
        "uid": "4PHCNnlWqhSpqwRlcrHpz3CLgQ82",
        "name": "thepela",
        "rank": 65
      },
      {
        "wpm": 52,
        "acc": 93.73,
        "timestamp": 1784080301000,
        "raw": 54.2,
        "consistency": 60.52,
        "uid": "D3Dli995WRbuZD9RSHOVKvYPozI2",
        "name": "TheLuisMi",
        "rank": 66
      },
      {
        "wpm": 51.59,
        "acc": 91.84,
        "timestamp": 1784088136000,
        "raw": 51.59,
        "consistency": 57.44,
        "uid": "cBkluuHUe5fI0ZR5SlOTtsCYxPi2",
        "name": "Phantasma",
        "discordId": "380545873253498882",
        "discordAvatar": "a_82b18919a78077e481d7dbe613fa80b9",
        "rank": 67
      },
      {
        "wpm": 48.39,
        "acc": 92.44,
        "timestamp": 1784111913000,
        "raw": 55.99,
        "consistency": 64.33,
        "uid": "HSCLwP2v7sUbhmFRw8Spr6umGZT2",
        "name": "Mauric10",
        "rank": 68
      },
      {
        "wpm": 46.2,
        "acc": 87.46,
        "timestamp": 1784102473000,
        "raw": 51.8,
        "consistency": 55.52,
        "uid": "DNAHAKWmmNQZB1KkXX0lImC1DLr2",
        "name": "ivanchuu_88",
        "rank": 69
      },
      {
        "wpm": 45.79,
        "acc": 94.88,
        "timestamp": 1784076119000,
        "raw": 48.39,
        "consistency": 63.32,
        "uid": "R1WaD0r028Z5te2L8RKfVoAG8263",
        "name": "lemoled3236R",
        "rank": 70
      },
      {
        "wpm": 44.4,
        "acc": 93.44,
        "timestamp": 1784133472000,
        "raw": 45.2,
        "consistency": 59.9,
        "uid": "IeJl0Cble6btzS8cElg7ig8YWoB2",
        "name": "fernm",
        "rank": 71
      },
      {
        "wpm": 42.79,
        "acc": 94.81,
        "timestamp": 1784154409000,
        "raw": 43.19,
        "consistency": 55.86,
        "uid": "KmiRIPEIY5RLYdlIRnxDZDBv62y2",
        "name": "carolinasamues.",
        "rank": 72
      },
      {
        "wpm": 42.39,
        "acc": 94.32,
        "timestamp": 1784098581000,
        "raw": 52.79,
        "consistency": 70.6,
        "uid": "KnoalMJVBVPXnHY9cDeb4uBhKRD2",
        "name": "Franmen",
        "rank": 73
      },
      {
        "wpm": 36.6,
        "acc": 89.72,
        "timestamp": 1784159996000,
        "raw": 36.6,
        "consistency": 59.6,
        "uid": "u5IdNZmYNWVLNGkbzn7XgiKQk2p1",
        "name": "Juan888",
        "rank": 74
      },
      {
        "wpm": 33.79,
        "acc": 93.99,
        "timestamp": 1784086551000,
        "raw": 33.79,
        "consistency": 43.64,
        "uid": "s1EpVfvUU5hV06GMGmYRtPyVyEz1",
        "name": "crivastian",
        "rank": 75
      },
      {
        "wpm": 26.8,
        "acc": 82.46,
        "timestamp": 1784078672000,
        "raw": 27.8,
        "consistency": 48.94,
        "uid": "zNri3ydgYDSFcxXhxzyZ8bYTKX73",
        "name": "VASCONE",
        "rank": 76
      },
      {
        "wpm": 26.39,
        "acc": 90.17,
        "timestamp": 1784119162000,
        "raw": 31.99,
        "consistency": 46.41,
        "uid": "VSkGXFBYDtMLYnZk6OkbsNkCdEz2",
        "name": "shihhaan",
        "rank": 77
      },
      {
        "wpm": 23,
        "acc": 97.5,
        "timestamp": 1784105210000,
        "raw": 23,
        "consistency": 36.65,
        "uid": "7FnPaq96KNgmedAsxT4fTz7okcF2",
        "name": "cmserii",
        "rank": 78
      },
      {
        "wpm": 19.4,
        "acc": 98.98,
        "timestamp": 1784106560000,
        "raw": 19.4,
        "consistency": 36.38,
        "uid": "DNXzMtpTjONqwPJ1ScVtjUQd3Rh2",
        "name": "Angel_Gamer-16",
        "rank": 79
      }
    ],
    "combinedEntryCount": 79
  },
  "pageSummaries": [
    {
      "page": 0,
      "url": "https://api.monkeytype.com/leaderboards/daily?pageSize=200&page=0&mode=time&language=spanish&daysBefore=1&mode2=%2260%22",
      "message": "Daily leaderboard retrieved",
      "reportedCount": 79,
      "reportedMinWpm": 19.4,
      "reportedPageSize": 200,
      "entriesFetched": 79
    },
    {
      "page": 1,
      "url": "https://api.monkeytype.com/leaderboards/daily?pageSize=200&page=1&mode=time&language=spanish&daysBefore=1&mode2=%2260%22",
      "message": "Daily leaderboard retrieved",
      "reportedCount": 79,
      "reportedMinWpm": 19.4,
      "reportedPageSize": 200,
      "entriesFetched": 0
    },
    {
      "page": 2,
      "url": "https://api.monkeytype.com/leaderboards/daily?pageSize=200&page=2&mode=time&language=spanish&daysBefore=1&mode2=%2260%22",
      "message": "Daily leaderboard retrieved",
      "reportedCount": 79,
      "reportedMinWpm": 19.4,
      "reportedPageSize": 200,
      "entriesFetched": 0
    },
    {
      "page": 3,
      "url": "https://api.monkeytype.com/leaderboards/daily?pageSize=200&page=3&mode=time&language=spanish&daysBefore=1&mode2=%2260%22",
      "message": "Daily leaderboard retrieved",
      "reportedCount": 79,
      "reportedMinWpm": 19.4,
      "reportedPageSize": 200,
      "entriesFetched": 0
    },
    {
      "page": 4,
      "url": "https://api.monkeytype.com/leaderboards/daily?pageSize=200&page=4&mode=time&language=spanish&daysBefore=1&mode2=%2260%22",
      "message": "Daily leaderboard retrieved",
      "reportedCount": 79,
      "reportedMinWpm": 19.4,
      "reportedPageSize": 200,
      "entriesFetched": 0
    }
  ]
}
